pynesweeper/__init__.py
pynesweeper/__main__.py
pynesweeper-0.1.0.dist-info/METADATA
pynesweeper-0.1.0.dist-info/WHEEL
pynesweeper-0.1.0.dist-info/entry_points.txt
pynesweeper-0.1.0.dist-info/licenses/LICENSE.txt
pynesweeper-0.1.0.dist-info/RECORD
